[{"id": "There must be user id", "problems": [1], "active_problem": 0, "разное": [1, 1], "планиметрия": [0, 0], "функционалка": [0, 0], "уравнения": [0, 0], "неравенства": [0, 0], "текстовые задачи": [0, 0], "теория чисел": [0, 0], "all": [1, 1]}, {"id": "Another user id", "problems": [1, 4, 3], "active_problem": 0, "разное": [1, 1], "планиметрия": [1, 1], "функционалка": [1, 1], "уравнения": [0, 0], "неравенства": [0, 0], "текстовые задачи": [0, 0], "теория чисел": [0, 0], "all": [3, 3]}, {"id": "One more user id", "problems": [], "active_problem": 1, "разное": [0, 0], "планиметрия": [0, 0], "функционалка": [0, 0], "уравнения": [0, 0], "неравенства": [0, 0], "текстовые задачи": [0, 0], "теория чисел": [0, 0], "all": [0, 0]}]